burst_tools/__init__.py
burst_tools/gpumem.py
burst_tools-0.1.8.data/scripts/gpumem
burst_tools-0.1.8.dist-info/METADATA
burst_tools-0.1.8.dist-info/WHEEL
burst_tools-0.1.8.dist-info/top_level.txt
burst_tools-0.1.8.dist-info/RECORD
