Metadata-Version: 2.1
Name: burst-tools
Version: 0.1.8
Summary: UNKNOWN
Home-page: UNKNOWN
License: UNKNOWN
Platform: UNKNOWN
Requires-Python: >=3
Requires-Dist: pynvml
